{
  "DataList": [
    {
      "EventContentId": 828,
      "UniqueId": 828001,
      "VoiceCondition": "DiceResultSuccess",
      "VoiceId": 4154991626
    },
    {
      "EventContentId": 828,
      "UniqueId": 828002,
      "VoiceCondition": "DiceResultSuccess",
      "VoiceId": 3282844901
    },
    {
      "EventContentId": 828,
      "UniqueId": 828003,
      "VoiceCondition": "DiceResultSuccess",
      "VoiceId": 3359469488
    },
    {
      "EventContentId": 828,
      "UniqueId": 828004,
      "VoiceCondition": "DiceResultSuccess",
      "VoiceId": 2556448196
    },
    {
      "EventContentId": 828,
      "UniqueId": 828011,
      "VoiceCondition": "DiceResultFailBattle",
      "VoiceId": 1179144759
    },
    {
      "EventContentId": 828,
      "UniqueId": 828012,
      "VoiceCondition": "DiceResultFailBattle",
      "VoiceId": 2283807959
    },
    {
      "EventContentId": 828,
      "UniqueId": 828013,
      "VoiceCondition": "DiceResultFailBattle",
      "VoiceId": 2666287
    },
    {
      "EventContentId": 828,
      "UniqueId": 828014,
      "VoiceCondition": "DiceResultFailBattle",
      "VoiceId": 3013499655
    },
    {
      "EventContentId": 828,
      "UniqueId": 828021,
      "VoiceCondition": "DiceResultFailRandom",
      "VoiceId": 2099031400
    },
    {
      "EventContentId": 828,
      "UniqueId": 828022,
      "VoiceCondition": "DiceResultFailRandom",
      "VoiceId": 2917174262
    },
    {
      "EventContentId": 828,
      "UniqueId": 828023,
      "VoiceCondition": "DiceResultFailRandom",
      "VoiceId": 508337470
    },
    {
      "EventContentId": 828,
      "UniqueId": 828024,
      "VoiceCondition": "DiceResultFailRandom",
      "VoiceId": 2463670588
    },
    {
      "EventContentId": 828,
      "UniqueId": 828031,
      "VoiceCondition": "EnemyDie",
      "VoiceId": 2403606103
    },
    {
      "EventContentId": 828,
      "UniqueId": 828032,
      "VoiceCondition": "EnemyDie",
      "VoiceId": 2433437022
    },
    {
      "EventContentId": 828,
      "UniqueId": 828033,
      "VoiceCondition": "EnemyDie",
      "VoiceId": 2049271254
    },
    {
      "EventContentId": 828,
      "UniqueId": 828034,
      "VoiceCondition": "EnemyDie",
      "VoiceId": 3558089172
    },
    {
      "EventContentId": 828,
      "UniqueId": 828041,
      "VoiceCondition": "TreasureBoxNormal",
      "VoiceId": 1235559581
    },
    {
      "EventContentId": 828,
      "UniqueId": 828042,
      "VoiceCondition": "TreasureBoxNormal",
      "VoiceId": 1295994673
    },
    {
      "EventContentId": 828,
      "UniqueId": 828043,
      "VoiceCondition": "TreasureBoxNormal",
      "VoiceId": 2237121170
    },
    {
      "EventContentId": 828,
      "UniqueId": 828044,
      "VoiceCondition": "TreasureBoxNormal",
      "VoiceId": 1403625333
    },
    {
      "EventContentId": 828,
      "UniqueId": 828051,
      "VoiceCondition": "TreasureBoxSpecial",
      "VoiceId": 3550172170
    },
    {
      "EventContentId": 828,
      "UniqueId": 828052,
      "VoiceCondition": "TreasureBoxSpecial",
      "VoiceId": 3470954644
    },
    {
      "EventContentId": 828,
      "UniqueId": 828053,
      "VoiceCondition": "TreasureBoxSpecial",
      "VoiceId": 3273194686
    },
    {
      "EventContentId": 828,
      "UniqueId": 828054,
      "VoiceCondition": "TreasureBoxSpecial",
      "VoiceId": 2242234034
    },
    {
      "EventContentId": 828,
      "UniqueId": 828061,
      "VoiceCondition": "FacilityResult",
      "VoiceId": 2240435780
    },
    {
      "EventContentId": 828,
      "UniqueId": 828062,
      "VoiceCondition": "FacilityResult",
      "VoiceId": 2119244785
    },
    {
      "EventContentId": 828,
      "UniqueId": 828063,
      "VoiceCondition": "FacilityResult",
      "VoiceId": 1460135151
    },
    {
      "EventContentId": 828,
      "UniqueId": 828064,
      "VoiceCondition": "FacilityResult",
      "VoiceId": 1359329573
    }
  ]
}
